tag_query/__init__.py
tag_query/compiler/__init__.py
tag_query/compiler/exceptions.py
tag_query/compiler/lexer.py
tag_query/compiler/tokens.py
tag_query-1.0.1.dist-info/licenses/LICENSE
tag_query-1.0.1.dist-info/METADATA
tag_query-1.0.1.dist-info/WHEEL
tag_query-1.0.1.dist-info/top_level.txt
tag_query-1.0.1.dist-info/RECORD
