Metadata-Version: 2.4
Name: tag_query
Version: 1.0.1
Summary: A Python package for robust querying of string lists in MongoDB.
Author-email: Zachary Westerman <westerman.zachary@gmail.com>
Project-URL: Homepage, https://github.com/ZacharyWesterman/tag_query
Project-URL: Issues, https://github.com/ZacharyWesterman/tag_query/issues
Classifier: Programming Language :: Python :: 3
Classifier: License :: OSI Approved :: GNU General Public License v3 (GPLv3)
Classifier: Operating System :: OS Independent
Requires-Python: >=3.0
License-File: LICENSE
Dynamic: license-file
